LICENSE
crak/__init__.py
crak/cli.py
crak-0.0.2.dist-info/entry_points.txt
crak-0.0.2.dist-info/LICENSE
crak-0.0.2.dist-info/WHEEL
crak-0.0.2.dist-info/METADATA
crak-0.0.2.dist-info/RECORD
